uhaf/__init__.py
uhaf/uhaf.py
uhaf/reference/uHAF2.2.0.xlsx
uhaf-0.1.8.dist-info/LICENSE
uhaf-0.1.8.dist-info/METADATA
uhaf-0.1.8.dist-info/WHEEL
uhaf-0.1.8.dist-info/top_level.txt
uhaf-0.1.8.dist-info/RECORD
