Metadata-Version: 2.2
Name: uhaf
Version: 0.1.8
Summary: Unified Hierarchical Annotation Framework for Single-cell Data
Home-page: https://github.com/SuperBianC/uhaf
Author: Haiyang Bian
Author-email: 253273104@qq.com
License: MIT
Classifier: Programming Language :: Python :: 3
Classifier: License :: OSI Approved :: MIT License
Classifier: Operating System :: OS Independent
Requires-Python: >=3.5
License-File: LICENSE
Requires-Dist: numpy==2.1.3
Requires-Dist: pandas==2.2.3
Dynamic: author
Dynamic: author-email
Dynamic: classifier
Dynamic: description
Dynamic: description-content-type
Dynamic: home-page
Dynamic: license
Dynamic: requires-dist
Dynamic: requires-python
Dynamic: summary
